isitdown/__init__.py
isitdown/__version__.py
isitdown/isitdown.py
isitdown/checks/__init__.py
isitdown/checks/base.py
isitdown/checks/http.py
isitdown/checks/ssh.py
isitdown/notifiers/__init__.py
isitdown-0.0.3.dist-info/METADATA
isitdown-0.0.3.dist-info/RECORD
isitdown-0.0.3.dist-info/WHEEL
isitdown-0.0.3.dist-info/top_level.txt
isitdown-0.0.3.dist-info/zip-safe
tests/__init__.py
tests/test_placeholder.py
